pyminitcp/__init__.py
pyminitcp/cli.py
pyminitcp/core.py
pyminitcp-2.0.0.dist-info/licenses/LICENSE
pyminitcp-2.0.0.dist-info/METADATA
pyminitcp-2.0.0.dist-info/WHEEL
pyminitcp-2.0.0.dist-info/entry_points.txt
pyminitcp-2.0.0.dist-info/top_level.txt
pyminitcp-2.0.0.dist-info/RECORD
