Metadata-Version: 2.4
Name: pyminitcp
Version: 2.0.0
Summary: A tiny, dependency-free Python library for TCP and UDP connectivity checks with IPv4/IPv6 and DNS support.
Home-page: https://github.com/roxy-wi/pyminitcp
Author: Pavel Loginov
Author-email: aidaho@roxy-wi.org
License: MIT
Keywords: tcp udp network check ipv6 ipv4 monitoring
Classifier: Programming Language :: Python :: 3
Classifier: License :: OSI Approved :: MIT License
Classifier: Operating System :: OS Independent
Classifier: Intended Audience :: Developers
Classifier: Topic :: System :: Networking
Requires-Python: >=3.7
License-File: LICENSE
Dynamic: author
Dynamic: author-email
Dynamic: classifier
Dynamic: description
Dynamic: description-content-type
Dynamic: home-page
Dynamic: keywords
Dynamic: license
Dynamic: license-file
Dynamic: requires-python
Dynamic: summary
